pyobimail/client.py
pyobimail/threads.py
pyobimail/utils.py
pyobimail/version.py
pyobimail-1.0.0.dist-info/LICENSE
pyobimail-1.0.0.dist-info/METADATA
pyobimail-1.0.0.dist-info/WHEEL
pyobimail-1.0.0.dist-info/top_level.txt
pyobimail-1.0.0.dist-info/zip-safe
pyobimail-1.0.0.dist-info/RECORD
