Metadata-Version: 2.1
Name: pyobimail
Version: 1.0.0
Summary: Python 3 library for mail and mail bots
Home-page: https://github.com/ObisoftDev/pyobimail
Author: ObisoftDev
Author-email: obisoftdev@gmail.com
License: The Unlicense (Unlicense)
Keywords: mail,download,stream,bots
Classifier: Development Status :: 5 - Production/Stable
Classifier: Environment :: Console
Classifier: Intended Audience :: Developers
Classifier: License :: OSI Approved :: The Unlicense (Unlicense)
Classifier: Natural Language :: English
Classifier: Operating System :: OS Independent
Classifier: Programming Language :: Python :: 3.6
Classifier: Programming Language :: Python :: 3.7
Classifier: Programming Language :: Python :: 3.8
Classifier: Programming Language :: Python :: 3.9
Classifier: Programming Language :: Python
Classifier: Topic :: Internet
Classifier: Topic :: Software Development :: Libraries :: Python Modules
Classifier: Topic :: Utilities
Requires-Python: >=3.6
License-File: LICENSE
Requires-Dist: secure-smtplib
Requires-Dist: secure-imaplib
Requires-Dist: bs4
Requires-Dist: requests
Requires-Dist: user-agent
